MANIFEST.in
setup.py
bin/runner
test/test_controller.py
test/test_model.py
test/test_view.py
testing_packaging/__init__.py
testing_packaging/controller.py
testing_packaging/model.py
testing_packaging/view.py
testing_packaging.egg-info/PKG-INFO
testing_packaging.egg-info/SOURCES.txt
testing_packaging.egg-info/dependency_links.txt
testing_packaging.egg-info/not-zip-safe
testing_packaging.egg-info/requires.txt
testing_packaging.egg-info/top_level.txt